setup.py
simpleacl/__init__.py
simpleacl/exceptions.py
simpleacl/middleware.py
simpleacl/tests.py
simpleacl.egg-info/PKG-INFO
simpleacl.egg-info/SOURCES.txt
simpleacl.egg-info/dependency_links.txt
simpleacl.egg-info/requires.txt
simpleacl.egg-info/top_level.txt