Metadata-Version: 1.1
Name: simpleacl
Version: 1.1.1
Summary: Simple Access Control list for Python
Home-page: https://github.com/kyleterry/simpleacl-py
Author: Ivan Zakrevsky
Author-email: ivzak@yandex.ru
License: LGPLv2+ License
Download-URL: http://cloud.github.com/downloads/kyleterry/simpleacl-py/simpleacl-1.1.1.tar.gz
Keywords: acl,simpleacl,access control list,auth list
Platform: UNKNOWN
Classifier: Development Status :: 4 - Beta
Classifier: Environment :: Console
Classifier: Intended Audience :: Developers
Classifier: License :: OSI Approved :: GNU Lesser General Public License v2 or later (LGPLv2+)
Classifier: Operating System :: OS Independent
Classifier: Programming Language :: Python
